watchdog/__init__.py
watchdog/library.py
watchdog/tests.py
watchdog/watchdog.py
checkniner_watchdog-0.6.1.dist-info/METADATA
checkniner_watchdog-0.6.1.dist-info/WHEEL
checkniner_watchdog-0.6.1.dist-info/entry_points.txt
checkniner_watchdog-0.6.1.dist-info/top_level.txt
checkniner_watchdog-0.6.1.dist-info/RECORD
