Metadata-Version: 2.1
Name: checkniner-watchdog
Version: 0.6.1
Summary: UNKNOWN
Home-page: UNKNOWN
Author: UNKNOWN
Author-email: UNKNOWN
License: UNKNOWN
Platform: UNKNOWN
Requires-Dist: certifi (==2019.6.16)
Requires-Dist: cffi (==1.12.3)
Requires-Dist: chardet (==3.0.4)
Requires-Dist: Click (==7.0)
Requires-Dist: idna (==2.8)
Requires-Dist: pycparser (==2.19)
Requires-Dist: PyNaCl (==1.3.0)
Requires-Dist: requests (==2.22.0)
Requires-Dist: six (==1.12.0)
Requires-Dist: urllib3 (==1.25.3)
